rtl/ALU.sv
module ALU #(
    parameter DATA_WIDTH = 32
              //CONTROL_SIGNAL = 1
) (
    input logic ALUctrl,
    input logic [DATA_WIDTH-1:0] ALUop1,
    input logic [DATA_WIDTH-1:0] ALUop2,
    output logic [DATA_WIDTH-1:0] ALUResult,
    output logic EQ //whether ALUop1 and ALUop2 are equal or not
    //can be either 0 or 1
);


//if (ALUctrl)
    //assign SUM = ALUop1 + ALUop2;
//else
    //if (ALUop1 - ALUop2 == {DATA_WIDTH{1'b0}})
        //assign EQ = 1'b1;
    //else
        //assign EQ = 1'b0;

    always_comb 
        casez(ALUctrl)
        1'b1: assign SUM = ALUop1 + ALUop2;
        1'b0: if (ALUop1 - ALUop2 == {DATA_WIDTH{1'b0}}) assign EQ = 1'b1; 
              else assign EQ = 1'b0;
        default: EQ = 1'b0;
        endcase
endmodule

rtl/RegFile.sv
module RegFile #(
    parameter ADDRESS_WIDTH = 16,
             //a0_WIDTH = 5,
              DATA_WIDTH = 32
              
) (
    input logic clk,
    input logic [ADDRESS_WIDTH-1:0] AD1,
    input logic [ADDRESS_WIDTH-1:0] AD2,
    input logic [ADDRESS_WIDTH-1:0] AD3,
    input logic WE3, //write enable
    input logic [DATA_WIDTH-1:0] WD3,
    output logic [DATA_WIDTH-1:0] RD1,
    output logic [DATA_WIDTH-1:0] RD2,
    output logic [DATA_WIDTH-1:0] a0
);

logic [DATA_WIDTH-1:0] regfile_array [2**ADDRESS_WIDTH-1:0];

//read ports should be asynchronous
//RD1 <= regfile_array[AD1];
//RD2 <= regfile_array[AD2];

//try
//assign RD1 = regfile_array[AD1];
//assign RD2 = regfile_array[AD2];

//write ports should be asynchronous
always_ff @ *
    begin
        RD1 = regfile_array[AD1];
        RD2 = regfile_array[AD2];
    end

always_ff @(posedge clk)
    begin
        if(WE3 == 1'b1)
            regfile_array[AD3] <= WD3;
    end

    //synchronous
    assign a0 = regfile_array[{16'b01010}];

//try
//a0 = regfile_array[ADDRESS_WIDTH{1'b0}]

endmodule

rtl/Sign_extend.sv
module Sign_extend (
    input logic         ImmSrc,
    input logic [31:0]  instr,
    output logic [31:0] ImmOp
);

always @ *
if (ImmSrc)
    if (instr[31])                                      // addi   12 bits immediate is from the instruction bit [31:20]
        assign ImmOp = ({20'hFFFFF, instr[31:20]});
    else
        assign ImmOp = ({20'b0, instr[31:20]});

else                                                    // bne   12 bits immediate is from the instruction bit [31,7,30:25,11:8]
    if (instr[31])
        assign ImmOp = ({20'hFFFFF, instr[31], instr[7], instr[30:25], instr[11:8]});
    else
        assign ImmOp = ({20'b0,  instr[31], instr[7], instr[30:25], instr[11:8]});

endmodule

rtl/Control_Unit.sv
module Control_Unit (
    input logic         EQ,
    input logic  [31:0]       instr,
    output logic        RegWrite,
    output logic        ALUctrl,
    output logic        ALUsrc,
    output logic        ImmSrc,
    output logic        PCsrc
);

logic [6:0]         op;
logic [2:0]         funct3;
logic [1:0]         ALUOp;
logic               Branch;
logic [21:0] dummyWire; //need to ensure all bits of signal are used [31:15, 11:7] 31-15+1=17; 11-7+1=5; 17+5=0

assign op = instr[6:0];
assign funct3 = instr[14:12];

assign dummyWire = {instr[31:15], instr[11:7]};

always_comb begin
    casez(op)
    default: begin
        assign dummyWire = 22'b0;
    end
    7'b0010011: begin
        assign RegWrite = 1;
        //ALUctrl = 0;
        assign ALUsrc = 1;
        assign ImmSrc = 1;
        assign ALUOp = 2'b10;
        assign Branch = 0;
    end
    7'b1100011: begin
        assign RegWrite = 0;
        //ALUctrl = 1;
        assign ALUsrc = 0;
        assign ImmSrc = 0;
        assign ALUOp = 2'b01;
        assign Branch = 1;
    end
    endcase

    casez(Branch)

    1'b1: if (EQ)
            assign PCsrc = 0;
          else
            assign PCsrc = 1;
    0'b0: assign PCsrc = 0;

    endcase

    casez(ALUOp)
    default: begin
        assign dummyWire = 22'b0;
    end
    2'b00: assign ALUctrl = 1;
    2'b01: assign ALUctrl = 0;
    2'b10: if (funct3 == 000)
            assign ALUctrl = 1;
           else assign ALUctrl = 0;
    endcase
end

endmodule

rtl/Instr_Mem.sv
module Instr_Mem # (
    parameter   ADDRESS_WIDTH = 32,
                DATA_WIDTH = 8,
                OUT_WIDTH = 32
)(
    input logic [ADDRESS_WIDTH-1:0] A,
    output logic [OUT_WIDTH-1:0] RD
);

logic [DATA_WIDTH-1:0] array [2**16-1:0];

initial begin
        $display ("Loading Instr_Mem.");
        $readmemh("counter.mem", array); 
end;

assign RD = {array [A+3], array [A+2], array [A+1], array[A+0]};

endmodule

rtl/ProgramCounter.sv
module ProgramCounter#(
    parameter WIDTH = 32
)(
    input logic      clk,
    input logic      rst,
    input logic [WIDTH-1:0]  next_PC,
    output logic [WIDTH-1:0]  PC
);

always_ff @(posedge clk, posedge rst)
    if(rst) PC <= {WIDTH{1'b0}};
    else    PC <= next_PC;

endmodule

rtl/PC_top.sv
module PC_top #(
    parameter WIDTH = 32
)(
    input logic clk,
    input logic rst,
    input logic PCsrc,
    input logic [WIDTH-1:0] ImmOp,
    output logic [WIDTH-1:0] PC
);

logic [WIDTH-1:0]  inc_PC;
logic [WIDTH-1:0]  branch_PC;
logic [WIDTH-1:0]  next_PC;
assign inc_PC = PC+4;
assign branch_PC = PC + ImmOp;

assign next_PC = PCsrc ? branch_PC : inc_PC;

  ProgramCounter ProgramCounter (
    .clk (clk),
    .rst (rst),
    .next_PC (next_PC),
    .PC(PC)
  );

endmodule

rtl/top.sv
module top #(
        parameter ADDRESS_WIDTH = 16,
                  DATA_WIDTH = 32
) (
    input logic clk,
    input logic rst,
    output logic [DATA_WIDTH-1:0] a0
);

//green 
logic [DATA_WIDTH-1:0] instr;
//blue
logic [ADDRESS_WIDTH-1:0] rs1;
logic [ADDRESS_WIDTH-1:0] rs2;
logic [ADDRESS_WIDTH-1:0] rd;
//purple
logic RegWrite;
logic ALUctrl;
logic ALUsrc;
logic ImmSrc;
logic PCsrc;
//yellow
logic [DATA_WIDTH-1:0] ALUop1;
logic [DATA_WIDTH-1:0] ALUop2;
logic [DATA_WIDTH-1:0] regOp2;
logic [DATA_WIDTH-1:0] ALUout;
logic EQ;
//orange
logic [DATA_WIDTH-1:0] ImmOp;
logic [DATA_WIDTH-1:0] PC;

assign rs1 = {{11'b0},instr[19:15]};
assign rs2 = {{11'b0},instr[24:20]};
assign rd = {{11'b0},instr[11:7]};



PC_top pc_top_instance (
    .clk (clk),
    .rst (rst),
    .ImmOp(ImmOp),
    .PCsrc (PCsrc),
    .PC (PC)
);

Instr_Mem instr_mem_instance (
    .A (PC),
    .RD (instr)
);

Control_Unit control_unit_instance(
    .EQ (EQ),
    .instr (instr),
    .RegWrite (RegWrite),
    .ALUctrl (ALUctrl),
    .ALUsrc (ALUsrc),
    .ImmSrc (ImmSrc),
    .PCsrc (PCsrc)
);

Sign_extend sign_extend_instance(
    .ImmSrc (ImmSrc),
    .instr (instr),
    .ImmOp (ImmOp)
);

RegFile reg_file_instance(
    .clk (clk),
    .AD1 (rs1),
    .AD2 (rs2),
    .AD3 (rd),
    .WE3 (RegWrite),
    .WD3 (ALUout),
    .RD1 (ALUop1),
    .RD2 (regOp2),
    .a0 (a0)
);

assign ALUop2 = ALUsrc ? ImmOp : regOp2;

ALU alu_instance(
    .ALUctrl (ALUctrl),
    .ALUop1 (ALUop1),
    .ALUop2 (ALUop2),
    .SUM (ALUout),
    .EQ (EQ)
);

endmodule

rtl/top.vcd
$version Generated by VerilatedVcd $end
$date Thu Dec  1 10:14:43 2022 $end
$timescale 1ps $end

 $scope module TOP $end
  $var wire 32 8 a0 [31:0] $end
  $var wire  1 6 clk $end
  $var wire  1 7 rst $end
  $scope module top $end
   $var wire 32 > ADDRESS_WIDTH [31:0] $end
   $var wire  1 ( ALUctrl $end
   $var wire 32 , ALUop1 [31:0] $end
   $var wire 32 - ALUop2 [31:0] $end
   $var wire 32 . ALUout [31:0] $end
   $var wire  1 ) ALUsrc $end
   $var wire 32 ? DATA_WIDTH [31:0] $end
   $var wire  1 / EQ $end
   $var wire 32 0 ImmOp [31:0] $end
   $var wire  1 * ImmSrc $end
   $var wire 32 : PC [31:0] $end
   $var wire  1 + PCsrc $end
   $var wire  1 ' RegWrite $end
   $var wire 32 8 a0 [31:0] $end
   $var wire  1 6 clk $end
   $var wire 32 # instr [31:0] $end
   $var wire 16 & rd [15:0] $end
   $var wire 32 9 regOp2 [31:0] $end
   $var wire 16 $ rs1 [15:0] $end
   $var wire 16 % rs2 [15:0] $end
   $var wire  1 7 rst $end
   $scope module alu_instance $end
    $var wire  1 ( ALUctrl $end
    $var wire 32 , ALUop1 [31:0] $end
    $var wire 32 - ALUop2 [31:0] $end
    $var wire 32 ? DATA_WIDTH [31:0] $end
    $var wire  1 / EQ $end
    $var wire 32 . SUM [31:0] $end
   $upscope $end
   $scope module control_unit_instance $end
    $var wire  2 3 ALUOp [1:0] $end
    $var wire  1 ( ALUctrl $end
    $var wire  1 ) ALUsrc $end
    $var wire  1 4 Branch $end
    $var wire  1 / EQ $end
    $var wire  1 * ImmSrc $end
    $var wire  1 + PCsrc $end
    $var wire  1 ' RegWrite $end
    $var wire 22 5 dummyWire [21:0] $end
    $var wire  3 2 funct3 [2:0] $end
    $var wire 32 # instr [31:0] $end
    $var wire  7 1 op [6:0] $end
   $upscope $end
   $scope module instr_mem_instance $end
    $var wire 32 : A [31:0] $end
    $var wire 32 ? ADDRESS_WIDTH [31:0] $end
    $var wire 32 @ DATA_WIDTH [31:0] $end
    $var wire 32 ? OUT_WIDTH [31:0] $end
    $var wire 32 # RD [31:0] $end
   $upscope $end
   $scope module pc_top_instance $end
    $var wire 32 0 ImmOp [31:0] $end
    $var wire 32 : PC [31:0] $end
    $var wire  1 + PCsrc $end
    $var wire 32 ? WIDTH [31:0] $end
    $var wire 32 < branch_PC [31:0] $end
    $var wire  1 6 clk $end
    $var wire 32 ; inc_PC [31:0] $end
    $var wire 32 = next_PC [31:0] $end
    $var wire  1 7 rst $end
    $scope module ProgramCounter $end
     $var wire 32 : PC [31:0] $end
     $var wire 32 ? WIDTH [31:0] $end
     $var wire  1 6 clk $end
     $var wire 32 = next_PC [31:0] $end
     $var wire  1 7 rst $end
    $upscope $end
   $upscope $end
   $scope module reg_file_instance $end
    $var wire 16 $ AD1 [15:0] $end
    $var wire 16 % AD2 [15:0] $end
    $var wire 16 & AD3 [15:0] $end
    $var wire 32 > ADDRESS_WIDTH [31:0] $end
    $var wire 32 ? DATA_WIDTH [31:0] $end
    $var wire 32 , RD1 [31:0] $end
    $var wire 32 9 RD2 [31:0] $end
    $var wire 32 . WD3 [31:0] $end
    $var wire  1 ' WE3 $end
    $var wire 32 8 a0 [31:0] $end
    $var wire  1 6 clk $end
   $upscope $end
   $scope module sign_extend_instance $end
    $var wire 32 0 ImmOp [31:0] $end
    $var wire  1 * ImmSrc $end
    $var wire 32 # instr [31:0] $end
   $upscope $end
  $upscope $end
 $upscope $end
$enddefinitions $end


#0
b00000000000000000000000000000000 #
b0000000000000000 $
b0000000000000000 %
b0000000000000000 &
0'
0(
0)
0*
0+
b00000000000000000000000000000000 ,
b00000000000000000000000000000000 -
b00000000000000000000000000000000 .
0/
b00000000000000000000000000000000 0
b0000000 1
b000 2
b00 3
04
b0000000000000000000000 5
16
07
b00000000000000000000000000000000 8
b00000000000000000000000000000000 9
b00000000000000000000000000000000 :
b00000000000000000000000000000100 ;
b00000000000000000000000000000000 <
b00000000000000000000000000000100 =
b00000000000000000000000000010000 >
b00000000000000000000000000100000 ?
b00000000000000000000000000001000 @
#1
b00001111111100000000001100010011 #
b0000000000011111 %
b0000000000000110 &
1'
1(
1)
1*
b00000000000000000000000011111111 -
b00000000000000000000000011111111 .
b00000000000000000000000011111111 0
b0010011 1
b10 3
b0000111111110000000110 5
06
b00000000000000000000000011111111 <
#2
b00000000000000000000010100010011 #
b0000000000000000 %
b0000000000001010 &
b00000000000000000000000000000000 -
b00000000000000000000000000000000 .
b00000000000000000000000000000000 0
b0000000000000000001010 5
16
b00000000000000000000000000000100 :
b00000000000000000000000000001000 ;
b00000000000000000000000000000100 <
b00000000000000000000000000001000 =
#3
06
#4
b00000000000000000000010110010011 #
b0000000000001011 &
b0000000000000000001011 5
16
b00000000000000000000000000001000 :
b00000000000000000000000000001100 ;
b00000000000000000000000000001000 <
b00000000000000000000000000001100 =
#5
06
#6
b00000000000001011000010100010011 #
b0000000000001011 $
b0000000000001010 &
b0000000000000101101010 5
16
b00000000000000000000000000001100 :
b00000000000000000000000000010000 ;
b00000000000000000000000000001100 <
b00000000000000000000000000010000 =
#7
06
#8
b00000000000101011000010110010011 #
b0000000000000001 %
b0000000000001011 &
b00000000000000000000000000000001 -
b00000000000000000000000000000001 .
b00000000000000000000000000000001 0
b0000000000010101101011 5
16
b00000000000000000000000000010000 :
b00000000000000000000000000010100 ;
b00000000000000000000000000010001 <
b00000000000000000000000000010100 =
#9
06
#10
b11111110011001011001100011100011 #
b0000000000000110 %
b0000000000010001 &
0'
0(
0)
0*
1+
b00000000000000000000000000000001 ,
b00000000000000000000000011111111 -
b11111111111111111111111111111000 0
b1100011 1
b001 2
b01 3
14
b1111111001100101110001 5
16
b00000000000000000000000011111111 9
b00000000000000000000000000010100 :
b00000000000000000000000000011000 ;
b00000000000000000000000000001100 <
b00000000000000000000000000001100 =
#11
06
#12
b00000000000001011000010100010011 #
b0000000000000000 %
b0000000000001010 &
1'
1(
1)
1*
0+
b00000000000000000000000000000000 -
b00000000000000000000000000000000 0
b0010011 1
b000 2
b10 3
04
b0000000000000101101010 5
16
b00000000000000000000000000000000 9
b00000000000000000000000000001100 :
b00000000000000000000000000010000 ;
b00000000000000000000000000010000 =
#13
06
#14
b00000000000101011000010110010011 #
b0000000000000001 %
b0000000000001011 &
b00000000000000000000000000000001 -
b00000000000000000000000000000010 .
b00000000000000000000000000000001 0
b0000000000010101101011 5
16
b00000000000000000000000000000001 8
b00000000000000000000000000010000 :
b00000000000000000000000000010100 ;
b00000000000000000000000000010001 <
b00000000000000000000000000010100 =
#15
06
#16
b11111110011001011001100011100011 #
b0000000000000110 %
b0000000000010001 &
0'
0(
0)
0*
1+
b00000000000000000000000000000010 ,
b00000000000000000000000011111111 -
b11111111111111111111111111111000 0
b1100011 1
b001 2
b01 3
14
b1111111001100101110001 5
16
b00000000000000000000000011111111 9
b00000000000000000000000000010100 :
b00000000000000000000000000011000 ;
b00000000000000000000000000001100 <
b00000000000000000000000000001100 =
#17
06
#18
b00000000000001011000010100010011 #
b0000000000000000 %
b0000000000001010 &
1'
1(
1)
1*
0+
b00000000000000000000000000000000 -
b00000000000000000000000000000000 0
b0010011 1
b000 2
b10 3
04
b0000000000000101101010 5
16
b00000000000000000000000000000000 9
b00000000000000000000000000001100 :
b00000000000000000000000000010000 ;
b00000000000000000000000000010000 =
#19
06
#20
b00000000000101011000010110010011 #
b0000000000000001 %
b0000000000001011 &
b00000000000000000000000000000001 -
b00000000000000000000000000000011 .
b00000000000000000000000000000001 0
b0000000000010101101011 5
16
b00000000000000000000000000000010 8
b00000000000000000000000000010000 :
b00000000000000000000000000010100 ;
b00000000000000000000000000010001 <
b00000000000000000000000000010100 =
#21
06
#22
b11111110011001011001100011100011 #
b0000000000000110 %
b0000000000010001 &
0'
0(
0)
0*
1+
b00000000000000000000000000000011 ,
b00000000000000000000000011111111 -
b11111111111111111111111111111000 0
b1100011 1
b001 2
b01 3
14
b1111111001100101110001 5
16
b00000000000000000000000011111111 9
b00000000000000000000000000010100 :
b00000000000000000000000000011000 ;
b00000000000000000000000000001100 <
b00000000000000000000000000001100 =
#23
06
#24
b00000000000001011000010100010011 #
b0000000000000000 %
b0000000000001010 &
1'
1(
1)
1*
0+
b00000000000000000000000000000000 -
b00000000000000000000000000000000 0
b0010011 1
b000 2
b10 3
04
b0000000000000101101010 5
16
b00000000000000000000000000000000 9
b00000000000000000000000000001100 :
b00000000000000000000000000010000 ;
b00000000000000000000000000010000 =
#25
06
#26
b00000000000101011000010110010011 #
b0000000000000001 %
b0000000000001011 &
b00000000000000000000000000000001 -
b00000000000000000000000000000100 .
b00000000000000000000000000000001 0
b0000000000010101101011 5
16
b00000000000000000000000000000011 8
b00000000000000000000000000010000 :
b00000000000000000000000000010100 ;
b00000000000000000000000000010001 <
b00000000000000000000000000010100 =
#27
06
#28
b11111110011001011001100011100011 #
b0000000000000110 %
b0000000000010001 &
0'
0(
0)
0*
1+
b00000000000000000000000000000100 ,
b00000000000000000000000011111111 -
b11111111111111111111111111111000 0
b1100011 1
b001 2
b01 3
14
b1111111001100101110001 5
16
b00000000000000000000000011111111 9
b00000000000000000000000000010100 :
b00000000000000000000000000011000 ;
b00000000000000000000000000001100 <
b00000000000000000000000000001100 =
#29
06
#30
b00000000000001011000010100010011 #
b0000000000000000 %
b0000000000001010 &
1'
1(
1)
1*
0+
b00000000000000000000000000000000 -
b00000000000000000000000000000000 0
b0010011 1
b000 2
b10 3
04
b0000000000000101101010 5
16
b00000000000000000000000000000000 9
b00000000000000000000000000001100 :
b00000000000000000000000000010000 ;
b00000000000000000000000000010000 =
#31
06
#32
b00000000000101011000010110010011 #
b0000000000000001 %
b0000000000001011 &
b00000000000000000000000000000001 -
b00000000000000000000000000000101 .
b00000000000000000000000000000001 0
b0000000000010101101011 5
16
b00000000000000000000000000000100 8
b00000000000000000000000000010000 :
b00000000000000000000000000010100 ;
b00000000000000000000000000010001 <
b00000000000000000000000000010100 =
#33
06
#34
b11111110011001011001100011100011 #
b0000000000000110 %
b0000000000010001 &
0'
0(
0)
0*
1+
b00000000000000000000000000000101 ,
b00000000000000000000000011111111 -
b11111111111111111111111111111000 0
b1100011 1
b001 2
b01 3
14
b1111111001100101110001 5
16
b00000000000000000000000011111111 9
b00000000000000000000000000010100 :
b00000000000000000000000000011000 ;
b00000000000000000000000000001100 <
b00000000000000000000000000001100 =
#35
06
#36
b00000000000001011000010100010011 #
b0000000000000000 %
b0000000000001010 &
1'
1(
1)
1*
0+
b00000000000000000000000000000000 -
b00000000000000000000000000000000 0
b0010011 1
b000 2
b10 3
04
b0000000000000101101010 5
16
b00000000000000000000000000000000 9
b00000000000000000000000000001100 :
b00000000000000000000000000010000 ;
b00000000000000000000000000010000 =
#37
06
#38
b00000000000101011000010110010011 #
b0000000000000001 %
b0000000000001011 &
b00000000000000000000000000000001 -
b00000000000000000000000000000110 .
b00000000000000000000000000000001 0
b0000000000010101101011 5
16
b00000000000000000000000000000101 8
b00000000000000000000000000010000 :
b00000000000000000000000000010100 ;
b00000000000000000000000000010001 <
b00000000000000000000000000010100 =
#39
06
#40
b11111110011001011001100011100011 #
b0000000000000110 %
b0000000000010001 &
0'
0(
0)
0*
1+
b00000000000000000000000000000110 ,
b00000000000000000000000011111111 -
b11111111111111111111111111111000 0
b1100011 1
b001 2
b01 3
14
b1111111001100101110001 5
16
b00000000000000000000000011111111 9
b00000000000000000000000000010100 :
b00000000000000000000000000011000 ;
b00000000000000000000000000001100 <
b00000000000000000000000000001100 =
#41
06
#42
b00000000000001011000010100010011 #
b0000000000000000 %
b0000000000001010 &
1'
1(
1)
1*
0+
b00000000000000000000000000000000 -
b00000000000000000000000000000000 0
b0010011 1
b000 2
b10 3
04
b0000000000000101101010 5
16
b00000000000000000000000000000000 9
b00000000000000000000000000001100 :
b00000000000000000000000000010000 ;
b00000000000000000000000000010000 =
#43
06
#44
b00000000000101011000010110010011 #
b0000000000000001 %
b0000000000001011 &
b00000000000000000000000000000001 -
b00000000000000000000000000000111 .
b00000000000000000000000000000001 0
b0000000000010101101011 5
16
b00000000000000000000000000000110 8
b00000000000000000000000000010000 :
b00000000000000000000000000010100 ;
b00000000000000000000000000010001 <
b00000000000000000000000000010100 =
#45
06
#46
b11111110011001011001100011100011 #
b0000000000000110 %
b0000000000010001 &
0'
0(
0)
0*
1+
b00000000000000000000000000000111 ,
b00000000000000000000000011111111 -
b11111111111111111111111111111000 0
b1100011 1
b001 2
b01 3
14
b1111111001100101110001 5
16
b00000000000000000000000011111111 9
b00000000000000000000000000010100 :
b00000000000000000000000000011000 ;
b00000000000000000000000000001100 <
b00000000000000000000000000001100 =
#47
06
#48
b00000000000001011000010100010011 #
b0000000000000000 %
b0000000000001010 &
1'
1(
1)
1*
0+
b00000000000000000000000000000000 -
b00000000000000000000000000000000 0
b0010011 1
b000 2
b10 3
04
b0000000000000101101010 5
16
b00000000000000000000000000000000 9
b00000000000000000000000000001100 :
b00000000000000000000000000010000 ;
b00000000000000000000000000010000 =
#49
06
#50
b00000000000101011000010110010011 #
b0000000000000001 %
b0000000000001011 &
b00000000000000000000000000000001 -
b00000000000000000000000000001000 .
b00000000000000000000000000000001 0
b0000000000010101101011 5
16
b00000000000000000000000000000111 8
b00000000000000000000000000010000 :
b00000000000000000000000000010100 ;
b00000000000000000000000000010001 <
b00000000000000000000000000010100 =
#51
06
#52
b11111110011001011001100011100011 #
b0000000000000110 %
b0000000000010001 &
0'
0(
0)
0*
1+
b00000000000000000000000000001000 ,
b00000000000000000000000011111111 -
b11111111111111111111111111111000 0
b1100011 1
b001 2
b01 3
14
b1111111001100101110001 5
16
b00000000000000000000000011111111 9
b00000000000000000000000000010100 :
b00000000000000000000000000011000 ;
b00000000000000000000000000001100 <
b00000000000000000000000000001100 =
#53
06
#54
b00000000000001011000010100010011 #
b0000000000000000 %
b0000000000001010 &
1'
1(
1)
1*
0+
b00000000000000000000000000000000 -
b00000000000000000000000000000000 0
b0010011 1
b000 2
b10 3
04
b0000000000000101101010 5
16
b00000000000000000000000000000000 9
b00000000000000000000000000001100 :
b00000000000000000000000000010000 ;
b00000000000000000000000000010000 =
#55
06
#56
b00000000000101011000010110010011 #
b0000000000000001 %
b0000000000001011 &
b00000000000000000000000000000001 -
b00000000000000000000000000001001 .
b00000000000000000000000000000001 0
b0000000000010101101011 5
16
b00000000000000000000000000001000 8
b00000000000000000000000000010000 :
b00000000000000000000000000010100 ;
b00000000000000000000000000010001 <
b00000000000000000000000000010100 =
#57
06
#58
b11111110011001011001100011100011 #
b0000000000000110 %
b0000000000010001 &
0'
0(
0)
0*
1+
b00000000000000000000000000001001 ,
b00000000000000000000000011111111 -
b11111111111111111111111111111000 0
b1100011 1
b001 2
b01 3
14
b1111111001100101110001 5
16
b00000000000000000000000011111111 9
b00000000000000000000000000010100 :
b00000000000000000000000000011000 ;
b00000000000000000000000000001100 <
b00000000000000000000000000001100 =
#59
06
#60
b00000000000001011000010100010011 #
b0000000000000000 %
b0000000000001010 &
1'
1(
1)
1*
0+
b00000000000000000000000000000000 -
b00000000000000000000000000000000 0
b0010011 1
b000 2
b10 3
04
b0000000000000101101010 5
16
b00000000000000000000000000000000 9
b00000000000000000000000000001100 :
b00000000000000000000000000010000 ;
b00000000000000000000000000010000 =
#61
06
#62
b00000000000101011000010110010011 #
b0000000000000001 %
b0000000000001011 &
b00000000000000000000000000000001 -
b00000000000000000000000000001010 .
b00000000000000000000000000000001 0
b0000000000010101101011 5
16
b00000000000000000000000000001001 8
b00000000000000000000000000010000 :
b00000000000000000000000000010100 ;
b00000000000000000000000000010001 <
b00000000000000000000000000010100 =
#63
06
#64
b11111110011001011001100011100011 #
b0000000000000110 %
b0000000000010001 &
0'
0(
0)
0*
1+
b00000000000000000000000000001010 ,
b00000000000000000000000011111111 -
b11111111111111111111111111111000 0
b1100011 1
b001 2
b01 3
14
b1111111001100101110001 5
16
b00000000000000000000000011111111 9
b00000000000000000000000000010100 :
b00000000000000000000000000011000 ;
b00000000000000000000000000001100 <
b00000000000000000000000000001100 =
#65
06
#66
b00000000000001011000010100010011 #
b0000000000000000 %
b0000000000001010 &
1'
1(
1)
1*
0+
b00000000000000000000000000000000 -
b00000000000000000000000000000000 0
b0010011 1
b000 2
b10 3
04
b0000000000000101101010 5
16
b00000000000000000000000000000000 9
b00000000000000000000000000001100 :
b00000000000000000000000000010000 ;
b00000000000000000000000000010000 =
#67
06
#68
b00000000000101011000010110010011 #
b0000000000000001 %
b0000000000001011 &
b00000000000000000000000000000001 -
b00000000000000000000000000001011 .
b00000000000000000000000000000001 0
b0000000000010101101011 5
16
b00000000000000000000000000001010 8
b00000000000000000000000000010000 :
b00000000000000000000000000010100 ;
b00000000000000000000000000010001 <
b00000000000000000000000000010100 =
#69
06
#70
b11111110011001011001100011100011 #
b0000000000000110 %
b0000000000010001 &
0'
0(
0)
0*
1+
b00000000000000000000000000001011 ,
b00000000000000000000000011111111 -
b11111111111111111111111111111000 0
b1100011 1
b001 2
b01 3
14
b1111111001100101110001 5
16
b00000000000000000000000011111111 9
b00000000000000000000000000010100 :
b00000000000000000000000000011000 ;
b00000000000000000000000000001100 <
b00000000000000000000000000001100 =
#71
06
#72
b00000000000001011000010100010011 #
b0000000000000000 %
b0000000000001010 &
1'
1(
1)
1*
0+
b00000000000000000000000000000000 -
b00000000000000000000000000000000 0
b0010011 1
b000 2
b10 3
04
b0000000000000101101010 5
16
b00000000000000000000000000000000 9
b00000000000000000000000000001100 :
b00000000000000000000000000010000 ;
b00000000000000000000000000010000 =
#73
06
#74
b00000000000101011000010110010011 #
b0000000000000001 %
b0000000000001011 &
b00000000000000000000000000000001 -
b00000000000000000000000000001100 .
b00000000000000000000000000000001 0
b0000000000010101101011 5
16
b00000000000000000000000000001011 8
b00000000000000000000000000010000 :
b00000000000000000000000000010100 ;
b00000000000000000000000000010001 <
b00000000000000000000000000010100 =
#75
06
#76
b11111110011001011001100011100011 #
b0000000000000110 %
b0000000000010001 &
0'
0(
0)
0*
1+
b00000000000000000000000000001100 ,
b00000000000000000000000011111111 -
b11111111111111111111111111111000 0
b1100011 1
b001 2
b01 3
14
b1111111001100101110001 5
16
b00000000000000000000000011111111 9
b00000000000000000000000000010100 :
b00000000000000000000000000011000 ;
b00000000000000000000000000001100 <
b00000000000000000000000000001100 =
#77
06
#78
b00000000000001011000010100010011 #
b0000000000000000 %
b0000000000001010 &
1'
1(
1)
1*
0+
b00000000000000000000000000000000 -
b00000000000000000000000000000000 0
b0010011 1
b000 2
b10 3
04
b0000000000000101101010 5
16
b00000000000000000000000000000000 9
b00000000000000000000000000001100 :
b00000000000000000000000000010000 ;
b00000000000000000000000000010000 =
#79
06
#80
b00000000000101011000010110010011 #
b0000000000000001 %
b0000000000001011 &
b00000000000000000000000000000001 -
b00000000000000000000000000001101 .
b00000000000000000000000000000001 0
b0000000000010101101011 5
16
b00000000000000000000000000001100 8
b00000000000000000000000000010000 :
b00000000000000000000000000010100 ;
b00000000000000000000000000010001 <
b00000000000000000000000000010100 =
#81
06
#82
b11111110011001011001100011100011 #
b0000000000000110 %
b0000000000010001 &
0'
0(
0)
0*
1+
b00000000000000000000000000001101 ,
b00000000000000000000000011111111 -
b11111111111111111111111111111000 0
b1100011 1
b001 2
b01 3
14
b1111111001100101110001 5
16
b00000000000000000000000011111111 9
b00000000000000000000000000010100 :
b00000000000000000000000000011000 ;
b00000000000000000000000000001100 <
b00000000000000000000000000001100 =
#83
06
#84
b00000000000001011000010100010011 #
b0000000000000000 %
b0000000000001010 &
1'
1(
1)
1*
0+
b00000000000000000000000000000000 -
b00000000000000000000000000000000 0
b0010011 1
b000 2
b10 3
04
b0000000000000101101010 5
16
b00000000000000000000000000000000 9
b00000000000000000000000000001100 :
b00000000000000000000000000010000 ;
b00000000000000000000000000010000 =
#85
06
#86
b00000000000101011000010110010011 #
b0000000000000001 %
b0000000000001011 &
b00000000000000000000000000000001 -
b00000000000000000000000000001110 .
b00000000000000000000000000000001 0
b0000000000010101101011 5
16
b00000000000000000000000000001101 8
b00000000000000000000000000010000 :
b00000000000000000000000000010100 ;
b00000000000000000000000000010001 <
b00000000000000000000000000010100 =
#87
06
#88
b11111110011001011001100011100011 #
b0000000000000110 %
b0000000000010001 &
0'
0(
0)
0*
1+
b00000000000000000000000000001110 ,
b00000000000000000000000011111111 -
b11111111111111111111111111111000 0
b1100011 1
b001 2
b01 3
14
b1111111001100101110001 5
16
b00000000000000000000000011111111 9
b00000000000000000000000000010100 :
b00000000000000000000000000011000 ;
b00000000000000000000000000001100 <
b00000000000000000000000000001100 =
#89
06
#90
b00000000000001011000010100010011 #
b0000000000000000 %
b0000000000001010 &
1'
1(
1)
1*
0+
b00000000000000000000000000000000 -
b00000000000000000000000000000000 0
b0010011 1
b000 2
b10 3
04
b0000000000000101101010 5
16
b00000000000000000000000000000000 9
b00000000000000000000000000001100 :
b00000000000000000000000000010000 ;
b00000000000000000000000000010000 =
#91
06
#92
b00000000000101011000010110010011 #
b0000000000000001 %
b0000000000001011 &
b00000000000000000000000000000001 -
b00000000000000000000000000001111 .
b00000000000000000000000000000001 0
b0000000000010101101011 5
16
b00000000000000000000000000001110 8
b00000000000000000000000000010000 :
b00000000000000000000000000010100 ;
b00000000000000000000000000010001 <
b00000000000000000000000000010100 =
#93
06
#94
b11111110011001011001100011100011 #
b0000000000000110 %
b0000000000010001 &
0'
0(
0)
0*
1+
b00000000000000000000000000001111 ,
b00000000000000000000000011111111 -
b11111111111111111111111111111000 0
b1100011 1
b001 2
b01 3
14
b1111111001100101110001 5
16
b00000000000000000000000011111111 9
b00000000000000000000000000010100 :
b00000000000000000000000000011000 ;
b00000000000000000000000000001100 <
b00000000000000000000000000001100 =
#95
06
#96
b00000000000001011000010100010011 #
b0000000000000000 %
b0000000000001010 &
1'
1(
1)
1*
0+
b00000000000000000000000000000000 -
b00000000000000000000000000000000 0
b0010011 1
b000 2
b10 3
04
b0000000000000101101010 5
16
b00000000000000000000000000000000 9
b00000000000000000000000000001100 :
b00000000000000000000000000010000 ;
b00000000000000000000000000010000 =
#97
06
