rtl/DataMemory.sv
module DataMemory #(
    parameter ADDRESS_WIDTH = 32,
              DATA_WIDTH = 32
)(
    input logic             clk,
    input logic             WE,
    input logic [ADDRESS_WIDTH-1:0] A,
    input logic [DATA_WIDTH-1:0] WD,
    output logic [DATA_WIDTH-1:0] RD
);

logic [DATA_WIDTH-1:0] dataMemory_array [2**ADDRESS_WIDTH-1:0];

always_ff @ *
    begin
        RD = dataMemory_array[AD1];
    end

always_ff @(posedge clk)
    begin
        if(WE == 1'b1)
            dataMemory_array[A] <= WD;
    end

endmodule

rtl/ALU.sv
module ALU #(
    parameter DATA_WIDTH = 32
              //CONTROL_SIGNAL = 1
) (
    input logic [2:0] ALUctrl,
    input logic [DATA_WIDTH-1:0] ALUop1,
    input logic [DATA_WIDTH-1:0] ALUop2,
    output logic [DATA_WIDTH-1:0] ALUResult,
    output logic Zero //whether ALUop1 and ALUop2 are equal or not
    //can be either 0 or 1
);


//if (ALUctrl)
    //assign SUM = ALUop1 + ALUop2;
//else
    //if (ALUop1 - ALUop2 == {DATA_WIDTH{1'b0}})
        //assign EQ = 1'b1;
    //else
        //assign EQ = 1'b0;

    always_comb 
        begin
        casez(ALUctrl)
        3'b000: assign ALUResult = ALUop1 + ALUop2;
        3'b001: assign ALUResult = ALUop1 - ALUop2;
        3'b110: assign ALUResult = ALUop2;
        default: Zero = 1'b0;
        endcase

        casez(ALUResult)
        32'b0:  assign Zero = 1'b1; 
        default: Zero = 1'b0;
        endcase
        end

endmodule

rtl/RegFile.sv
module RegFile #(
    parameter ADDRESS_WIDTH = 16,
             //a0_WIDTH = 5,
              DATA_WIDTH = 32
              
) (
    input logic clk,
    input logic [ADDRESS_WIDTH-1:0] AD1,
    input logic [ADDRESS_WIDTH-1:0] AD2,
    input logic [ADDRESS_WIDTH-1:0] AD3,
    input logic WE3, //write enable
    input logic [DATA_WIDTH-1:0] WD3,
    output logic [DATA_WIDTH-1:0] RD1,
    output logic [DATA_WIDTH-1:0] RD2,
    output logic [DATA_WIDTH-1:0] a0
);

logic [DATA_WIDTH-1:0] regfile_array [2**ADDRESS_WIDTH-1:0];

//read ports should be asynchronous
//RD1 <= regfile_array[AD1];
//RD2 <= regfile_array[AD2];

//try
//assign RD1 = regfile_array[AD1];
//assign RD2 = regfile_array[AD2];

//write ports should be asynchronous
always_ff @ *
    begin
        RD1 = regfile_array[AD1];
        RD2 = regfile_array[AD2];
    end

always_ff @(posedge clk)
    begin
        if(WE3 == 1'b1)
            regfile_array[AD3] <= WD3;
    end

    //synchronous
    assign a0 = regfile_array[{16'b01010}];

//try
//a0 = regfile_array[ADDRESS_WIDTH{1'b0}]

endmodule

rtl2/Sign_extend.sv
module Sign_extend (
    input logic [2:0]   ImmSrc,
    input logic [31:0]  instr,
    output logic [31:0] ImmExt
);

    logic dummy_wire;

always_comb

    casez(ImmSrc)
    default: assign dummy_wire = 0; 
    3'b000: if (instr[31])                                      // I type   12 bits immediate is from the instruction bit [31:20]
                assign ImmExt = ({20'hFFFFF, instr[31:20]});
            else
                assign ImmExt = ({20'b0, instr[31:20]});

    3'b001: if (instr[31])                                      // S type 
                assign ImmExt = ({20'hFFFFF, instr[31:25], instr[11:7]});
            else
                assign ImmExt = ({20'b0, instr[31:25], instr[11:7]});

    3'b010: if (instr[31])                                      // B type
                assign ImmExt = ({20'hFFFFF, instr[31], instr[7], instr[30:25], instr[11:8]});
            else
                assign ImmExt = ({20'b0,  instr[31], instr[7], instr[30:25], instr[11:8]});
    
    3'b011: if (instr[31])                                      // J type
                assign ImmExt = ({20'hFFFFF, instr[31], instr[19:12], instr[20], instr[30:21]});
            else
                assign ImmExt = ({20'b0, instr[31], instr[19:12], instr[20], instr[30:21]});

    3'b100: assign ImmExt = ({instr[31:12], 12'b0});            // U type

    endcase
    
endmodule

rtl/Control_Unit.sv
module Control_Unit (
    input logic         Zero,
    input logic  [31:0] instr,
    output logic        RegWrite,
    output logic [2:0]  ALUctrl,
    output logic        ALUsrc,
    output logic [2:0]  ImmSrc,
    output logic        PCsrc,
    output logic        ResultSrc,
    output logic        MemWrite,
    output logic        MUXJUMP,                // MUXJUMP = 0 so that register write in result. MUXJUMP = 1 so that register write in PC+4
    output logic        JUMPRT     
);

logic [6:0]         op;
logic [2:0]         funct3;
logic [6:0]         funct7;
logic [1:0]         ALUOp;
logic [1:0]         opfunct7;
//logic               Branch;
logic               dummy;


assign op = instr[6:0];
assign funct3 = instr[14:12];
assign funct7 = instr[31:25];
assign opfunct7 = {op[5],funct7[5]};

always_comb begin
    casez(op)

    default: assign dummy = 0;

    7'b0010011: begin                      // Immediate ALU operation
        assign RegWrite = 1;
        assign ImmSrc = 3'b000;
        assign ALUsrc = 1;
        assign MemWrite = 0;
        assign ResultSrc = 0;
        //assign Branch = 0;
        assign ALUOp = 2'b10;
        assign MUXJUMP = 0;
        assign PCsrc = 0;
        assign JUMPRT = 0;
    end

    7'b0000011: begin                     //  Load
        assign RegWrite = 1;
        assign ImmSrc = 3'b000;
        assign ALUsrc = 1;
        assign MemWrite = 0;
        assign ResultSrc = 1;
        //assign Branch = 0;
        assign ALUOp = 2'b00;
        assign MUXJUMP = 0;
        assign PCsrc = 0;
        assign JUMPRT = 0;
    end

    7'b0100011: begin                     // store
        assign RegWrite = 0;
        assign ImmSrc = 3'b001;
        assign ALUsrc = 1;
        assign MemWrite = 1;
        assign ResultSrc = 0;
        //assign Branch = 0;
        assign ALUOp = 2'b00;
        assign MUXJUMP = 0;
        assign PCsrc = 0;
        assign JUMPRT = 0;
    end

    7'b0110011: begin                     // R type
        assign RegWrite = 1;
        assign ImmSrc = 3'b000;
        assign ALUsrc = 0;
        assign MemWrite = 0;
        assign ResultSrc = 0;
        //assign Branch = 0;
        assign ALUOp = 2'b10;
        assign MUXJUMP = 0;
        assign PCsrc = 0;
        assign JUMPRT = 0;
    end

    7'b1100011: begin                      // Branch
        assign RegWrite = 0;
        assign ImmSrc = 3'b010;
        assign ALUsrc = 0;
        assign MemWrite = 0;
        assign ResultSrc = 0;
        //assign Branch = 1;
        assign ALUOp = 2'b01;
        assign MUXJUMP = 0;
        assign JUMPRT = 0;
        
        casez(funct3)
            default: assign dummy = 0;
            3'b000: if (Zero)
                        assign PCsrc = 1;
                    else
                        assign PCsrc = 0;
            3'b001: if (Zero)
                        assign PCsrc = 0;
                    else
                        assign PCsrc = 1;
        endcase
    end

    7'b1100111: begin                      // jump and link register
        assign RegWrite = 1;
        assign ImmSrc = 3'b000;
        assign ALUsrc = 1;
        assign MemWrite = 0;
        assign ResultSrc = 0;
        //assign Branch = 1;
        assign ALUOp = 2'b00;
        assign MUXJUMP = 1;
        assign PCsrc = 1;
        assign JUMPRT = 1;
    end

    7'b1101111: begin                      // jump and link
        assign RegWrite = 1;
        assign ImmSrc = 3'b011;
        assign ALUsrc = 0;
        assign MemWrite = 0;
        assign ResultSrc = 0;
        //assign Branch = 1;
        assign ALUOp = 2'b00;
        assign MUXJUMP = 1;
        assign PCsrc = 1;
        assign JUMPRT = 0;
    end

    7'b0110111: begin                      // load upper immediate
        assign RegWrite = 1;
        assign ImmSrc = 3'b100;
        assign ALUsrc = 1;
        assign MemWrite = 0;
        assign ResultSrc = 0;
        //assign Branch = 1;
        assign ALUOp = 2'b11;
        assign MUXJUMP = 0;
        assign PCsrc = 0;
        assign JUMPRT = 0;
    end
    endcase

    casez(ALUOp)
    2'b00: assign ALUctrl = 000;
    2'b01: assign ALUctrl = 001;
    2'b10: casez(funct3)
           3'b000: if (op == 0110011 && opfunct7 == 2'b11)   assign ALUctrl = 3'b001;          //subtract
                   else  assign ALUctrl = 3'b000;                      // add
           3'b010: assign ALUctrl = 3'b101;                            // set less than
           3'b110: assign ALUctrl = 3'b011;                            // or
           3'b111: assign ALUctrl = 3'b010;                            // and
           3'b001: assign ALUctrl = 3'b100;                            // shift left
           endcase
    2'b11: assign ALUctrl = 3'b110;                                       // ALUResult = SrcB
    endcase
end

endmodule

rtl/Instr_Mem.sv
module Instr_Mem # (
    parameter   ADDRESS_WIDTH = 32,
                DATA_WIDTH = 8,
                OUT_WIDTH = 32
)(
    input logic [ADDRESS_WIDTH-1:0] A,
    output logic [OUT_WIDTH-1:0] RD
);

logic [11:0] addr = A[11:0] ,

logic [DATA_WIDTH-1:0] array [2**12-1:0];

initial begin
        $display ("Loading Instr_Mem.");
        $readmemh("counter.mem", array); 
end;

assign RD = {array [addr+3], array [addr+2], array [addr+1], array[addr+0]};

endmodule

rtl2/ProgramCounter.sv
module ProgramCounter#(
    parameter WIDTH = 32
)(
    input logic      clk,
    input logic      rst,
    input logic [WIDTH-1:0]  PCNext,
    output logic [WIDTH-1:0]  PC
);

always_ff @(posedge clk, posedge rst)
    if(rst) PC <= 32'hBFC00000;
    else    PC <= PCNext;

endmodule

rtl/PC_top.sv
module PC_top #(
    parameter WIDTH = 32
)(
    input logic clk,
    input logic rst,
    input logic PCsrc,
    input logic JUMPRT,
    input logic [WIDTH-1:0] ImmOp,
    input logic [WIDTH-1:0] Result,
    output logic [WIDTH-1:0] PC
);

logic [WIDTH-1:0]  inc_PC;
logic [WIDTH-1:0]  branch_PC;
logic [WIDTH-1:0]  PCNext;
logic [WIDTH-1:0] ReturnMultiplexerOutput;
assign inc_PC = PC+4;
assign branch_PC = PC + ImmOp;

assign ReturnMultiplexerOutput = JUMPRT ? Result : branch_PC;//jump multiplexer
assign PCNext = PCsrc ? ReturnMultiplexerOutput : inc_PC;

  ProgramCounter ProgramCounter (
    .clk (clk),
    .rst (rst),
    .PCNext (PCNext),
    .PC(PC)
  );

endmodule

rtl/top.sv
module top #(
        parameter ADDRESS_WIDTH = 16,
                  DATA_WIDTH = 32
) (
    input logic clk,
    input logic rst,
    input logic TRIGGERSEL,
    output logic [DATA_WIDTH-1:0] a0
);

//green 
logic [DATA_WIDTH-1:0] instr;
//blue
logic [ADDRESS_WIDTH-1:0] rs1;
logic [ADDRESS_WIDTH-1:0] rs2;
logic [ADDRESS_WIDTH-1:0] rd;
//purple
logic RegWrite;
logic ALUctrl;
logic ALUsrc;
logic ImmSrc;
logic PCsrc;
logic MemWrite;
logic JUMPRT;
logic MUXJUMP;
logic Zero;
logic ResultSrc;
//yellow
logic [DATA_WIDTH-1:0] ALUop1;
logic [DATA_WIDTH-1:0] ALUop2;
logic [DATA_WIDTH-1:0] regOp2;
logic [DATA_WIDTH-1:0] ALUout;
logic EQ;
//orange
logic [DATA_WIDTH-1:0] ImmOp;
logic [DATA_WIDTH-1:0] PC;
logic [DATA_WIDTH-1:0] MUXJUMPOutput;
//dataMemory
logic [DATA_WIDTH-1:0] ReadData;
logic [DATA_WIDTH-1:0] TriggerOutput;
logic [DATA_WIDTH-1:0] Result;

assign rs1 = {{11'b0},instr[19:15]};
assign rs2 = {{11'b0},instr[24:20]};
assign rd = {{11'b0},instr[11:7]};



PC_top pc_top_instance (
    .clk (clk),
    .rst (rst),
    .ImmOp(ImmOp),
    .PCsrc (PCsrc),
    .PC (PC),
    .JUMPRT(JUMPRT),
    .Result(Result)
);

Instr_Mem instr_mem_instance (
    .A (PC),
    .RD (instr)
);

Control_Unit control_unit_instance(
    .Zero (Zero),
    .instr (instr),
    .RegWrite (RegWrite),
    .ALUctrl (ALUctrl),
    .ALUsrc (ALUsrc),
    .ImmSrc (ImmSrc),
    .PCsrc (PCsrc),
    .ResultSrc (ResultSrc),
    .MemWrite(MemWrite),
    .JUMPRT(JUMPRT),
    .MUXJUMP(MUXJUMP)
);

Sign_extend sign_extend_instance(
    .ImmSrc (ImmSrc),
    .instr (instr),
    .ImmExt (ImmOp)
);

assign MUXJUMPOutput = MUXJUMP ? PC+4 : Result;

RegFile reg_file_instance(
    .clk (clk),
    .AD1 (rs1),
    .AD2 (rs2),
    .AD3 (rd),
    .WE3 (RegWrite),
    .WD3 (MUXJUMPOutput),
    .RD1 (ALUop1),
    .RD2 (regOp2),
    .a0 (a0)
);

assign ALUop2 = ALUsrc ? ImmOp : regOp2;

ALU alu_instance(
    .ALUctrl (ALUctrl),
    .ALUop1 (ALUop1),
    .ALUop2 (ALUop2),
    .ALUResult (ALUout),
    .Zero (Zero)
);

DataMemory data_memory_instance(
    .clk (clk),
    .WE (MemWrite),
    .A (ALUout),
    .WD (regOp2),
    .RD (ReadData)
);

assign TriggerOutput = TRIGGERSEL ? ReadData : ALUout; //Trigger Mux
assign Result = ResultSrc ? TriggerOutput : ALUout; //Mux for data memory


endmodule

rtl/top.vcd
$version Generated by VerilatedVcd $end
$date Wed Dec  7 16:24:28 2022 $end
$timescale 1ps $end

 $scope module TOP $end
  $var wire  1 G TRIGGERSEL $end
  $var wire 32 H a0 [31:0] $end
  $var wire  1 E clk $end
  $var wire  1 F rst $end
  $scope module top $end
   $var wire 32 O ADDRESS_WIDTH [31:0] $end
   $var wire  1 ( ALUctrl $end
   $var wire 32 1 ALUop1 [31:0] $end
   $var wire 32 2 ALUop2 [31:0] $end
   $var wire 32 4 ALUout [31:0] $end
   $var wire  1 ) ALUsrc $end
   $var wire 32 P DATA_WIDTH [31:0] $end
   $var wire  1 Q EQ $end
   $var wire 32 5 ImmOp [31:0] $end
   $var wire  1 * ImmSrc $end
   $var wire  1 - JUMPRT $end
   $var wire  1 . MUXJUMP $end
   $var wire 32 I MUXJUMPOutput [31:0] $end
   $var wire  1 , MemWrite $end
   $var wire 32 6 PC [31:0] $end
   $var wire  1 + PCsrc $end
   $var wire 32 J ReadData [31:0] $end
   $var wire  1 ' RegWrite $end
   $var wire 32 L Result [31:0] $end
   $var wire  1 0 ResultSrc $end
   $var wire  1 G TRIGGERSEL $end
   $var wire 32 K TriggerOutput [31:0] $end
   $var wire  1 / Zero $end
   $var wire 32 H a0 [31:0] $end
   $var wire  1 E clk $end
   $var wire 32 # instr [31:0] $end
   $var wire 16 & rd [15:0] $end
   $var wire 32 3 regOp2 [31:0] $end
   $var wire 16 $ rs1 [15:0] $end
   $var wire 16 % rs2 [15:0] $end
   $var wire  1 F rst $end
   $scope module alu_instance $end
    $var wire 32 4 ALUResult [31:0] $end
    $var wire  3 7 ALUctrl [2:0] $end
    $var wire 32 1 ALUop1 [31:0] $end
    $var wire 32 2 ALUop2 [31:0] $end
    $var wire 32 P DATA_WIDTH [31:0] $end
    $var wire  1 / Zero $end
   $upscope $end
   $scope module control_unit_instance $end
    $var wire  2 = ALUOp [1:0] $end
    $var wire  3 8 ALUctrl [2:0] $end
    $var wire  1 ) ALUsrc $end
    $var wire  3 9 ImmSrc [2:0] $end
    $var wire  1 - JUMPRT $end
    $var wire  1 . MUXJUMP $end
    $var wire  1 , MemWrite $end
    $var wire  1 + PCsrc $end
    $var wire  1 ' RegWrite $end
    $var wire  1 0 ResultSrc $end
    $var wire  1 / Zero $end
    $var wire  1 ? dummy $end
    $var wire  3 ; funct3 [2:0] $end
    $var wire  7 < funct7 [6:0] $end
    $var wire 32 # instr [31:0] $end
    $var wire  7 : op [6:0] $end
    $var wire  2 > opfunct7 [1:0] $end
   $upscope $end
   $scope module data_memory_instance $end
    $var wire 32 4 A [31:0] $end
    $var wire 32 P ADDRESS_WIDTH [31:0] $end
    $var wire 32 P DATA_WIDTH [31:0] $end
    $var wire 32 J RD [31:0] $end
    $var wire 32 3 WD [31:0] $end
    $var wire  1 , WE $end
    $var wire  1 E clk $end
   $upscope $end
   $scope module instr_mem_instance $end
    $var wire 32 6 A [31:0] $end
    $var wire 32 P ADDRESS_WIDTH [31:0] $end
    $var wire 32 R DATA_WIDTH [31:0] $end
    $var wire 32 P OUT_WIDTH [31:0] $end
    $var wire 32 # RD [31:0] $end
    $var wire 12 @ addr [11:0] $end
   $upscope $end
   $scope module pc_top_instance $end
    $var wire 32 5 ImmOp [31:0] $end
    $var wire  1 - JUMPRT $end
    $var wire 32 6 PC [31:0] $end
    $var wire 32 M PCNext [31:0] $end
    $var wire  1 + PCsrc $end
    $var wire 32 L Result [31:0] $end
    $var wire 32 N ReturnMultiplexerOutput [31:0] $end
    $var wire 32 P WIDTH [31:0] $end
    $var wire 32 B branch_PC [31:0] $end
    $var wire  1 E clk $end
    $var wire 32 A inc_PC [31:0] $end
    $var wire  1 F rst $end
    $scope module ProgramCounter $end
     $var wire 32 6 PC [31:0] $end
     $var wire 32 M PCNext [31:0] $end
     $var wire 32 P WIDTH [31:0] $end
     $var wire  1 E clk $end
     $var wire  1 F rst $end
    $upscope $end
   $upscope $end
   $scope module reg_file_instance $end
    $var wire 16 $ AD1 [15:0] $end
    $var wire 16 % AD2 [15:0] $end
    $var wire 16 & AD3 [15:0] $end
    $var wire 32 O ADDRESS_WIDTH [31:0] $end
    $var wire 32 P DATA_WIDTH [31:0] $end
    $var wire 32 1 RD1 [31:0] $end
    $var wire 32 3 RD2 [31:0] $end
    $var wire 32 I WD3 [31:0] $end
    $var wire  1 ' WE3 $end
    $var wire 32 H a0 [31:0] $end
    $var wire  1 E clk $end
   $upscope $end
   $scope module sign_extend_instance $end
    $var wire 32 5 ImmExt [31:0] $end
    $var wire  3 C ImmSrc [2:0] $end
    $var wire  1 D dummy_wire $end
    $var wire 32 # instr [31:0] $end
   $upscope $end
  $upscope $end
 $upscope $end
$enddefinitions $end


#0
b00000000000000000000000000000000 #
b0000000000000000 $
b0000000000000000 %
b0000000000000000 &
0'
0(
0)
0*
0+
0,
0-
0.
0/
00
b00000000000000000000000000000000 1
b00000000000000000000000000000000 2
b00000000000000000000000000000000 3
b00000000000000000000000000000000 4
b00000000000000000000000000000000 5
b00000000000000000000000000000000 6
b000 7
b000 8
b000 9
b0000000 :
b000 ;
b0000000 <
b00 =
b00 >
0?
b000000000000 @
b00000000000000000000000000000100 A
b00000000000000000000000000000000 B
b000 C
0D
1E
0F
0G
b00000000000000000000000000000000 H
b00000000000000000000000000000000 I
b00000000000000000000000000000000 J
b00000000000000000000000000000000 K
b00000000000000000000000000000000 L
b00000000000000000000000000000100 M
b00000000000000000000000000000000 N
b00000000000000000000000000010000 O
b00000000000000000000000000100000 P
0Q
b00000000000000000000000000001000 R
#1
b00000000000000000010001110110111 #
b0000000000000111 &
1'
1)
1/
b110 8
b100 9
b0110111 :
b010 ;
b11 =
b10 >
0E
#2
b00000000000000111010110100000011 #
b0000000000000111 $
b0000000000011010 &
10
b00000000000000000000000000000100 6
b000 8
b000 9
b0000011 :
b00 =
b00 >
b000000000100 @
b00000000000000000000000000001000 A
b00000000000000000000000000000100 B
1E
1F
b00000000000000000000000000001000 M
b00000000000000000000000000000100 N
#3
b00000000000000000010001110110111 #
b0000000000000000 $
b0000000000000111 &
00
b10111111110000000000000000000000 6
b110 8
b100 9
b0110111 :
b11 =
b10 >
b000000000000 @
b10111111110000000000000000000100 A
b10111111110000000000000000000000 B
0E
b10111111110000000000000000000100 M
b10111111110000000000000000000000 N
#4
1E
#5
0E
#6
1E
0F
#7
0E
#8
b00000000000000111010110100000011 #
b0000000000000111 $
b0000000000011010 &
10
b10111111110000000000000000000100 6
b000 8
b000 9
b0000011 :
b00 =
b00 >
b000000000100 @
b10111111110000000000000000001000 A
b10111111110000000000000000000100 B
1E
1G
b10111111110000000000000000001000 M
b10111111110000000000000000000100 N
#9
0E
#10
b11111110000011010000111011100011 #
b0000000000011010 $
b0000000000011101 &
0'
1(
0)
1+
00
b11111111111111111111111111100000 5
b10111111110000000000000000001000 6
b001 7
b001 8
b010 9
b1100011 :
b000 ;
b1111111 <
b01 =
b11 >
b000000001000 @
b10111111110000000000000000001100 A
b10111111101111111111111111101000 B
1E
b10111111101111111111111111101000 M
b10111111101111111111111111101000 N
#11
0E
#12
b00000000000000000000000000000000 #
b0000000000000000 $
b0000000000000000 &
b00000000000000000000000000000000 5
b10111111101111111111111111101000 6
b0000000 :
b0000000 <
b00 >
b111111101000 @
b10111111101111111111111111101100 A
1E
