pipelining2/DataMemory.sv
module DataMemory #(
    parameter ADDRESS_WIDTH = 32,
              DATA_WIDTH = 32
)(
    input logic             clk,
    input logic             WE,
    input logic [ADDRESS_WIDTH-1:0] A,
    input logic [DATA_WIDTH-1:0] WD,
    output logic [DATA_WIDTH-1:0] RD
);

logic [DATA_WIDTH-1:0] dataMemory_array [2**17-1:0];

always_ff @ *
    begin
        RD = dataMemory_array[A];
    end

always_ff @(posedge clk)
    begin
        if(WE == 1'b1)
            dataMemory_array[A] <= WD;
    end

endmodule

rtl2/ALU.sv
module ALU #(
    parameter DATA_WIDTH = 32
              //CONTROL_SIGNAL = 1
) (
    input logic [2:0] ALUctrl,
    input logic [DATA_WIDTH-1:0] ALUop1,
    input logic [DATA_WIDTH-1:0] ALUop2,
    output logic [DATA_WIDTH-1:0] ALUResult,
    output logic Zero //whether ALUop1 and ALUop2 are equal or not
    //can be either 0 or 1
);

    always_comb 
        begin
        casez(ALUctrl)
        3'b000: assign ALUResult = ALUop1 + ALUop2;
        3'b001: assign ALUResult = ALUop1 - ALUop2;
        3'b110: assign ALUResult = ALUop2; //load upper immediate
        default: Zero = 1'b0;
        endcase

        casez(ALUResult)
        32'b0:  assign Zero = 1'b1; 
        default: Zero = 1'b0;
        endcase
        end

endmodule

rtl3/RegFile.sv
module RegFile #(
    parameter ADDRESS_WIDTH = 16,
             //a0_WIDTH = 5,
              DATA_WIDTH = 32
              
) (
    input logic clk,
    input logic [ADDRESS_WIDTH-1:0] AD1,
    input logic [ADDRESS_WIDTH-1:0] AD2,
    input logic [ADDRESS_WIDTH-1:0] AD3,
    input logic WE3, //write enable
    input logic [DATA_WIDTH-1:0] WD3,
    output logic [DATA_WIDTH-1:0] RD1,
    output logic [DATA_WIDTH-1:0] RD2,
    output logic [DATA_WIDTH-1:0] a0
);

logic [DATA_WIDTH-1:0] regfile_array [2**ADDRESS_WIDTH-1:0];

//read ports should be asynchronous
always_ff @ *
    begin
        RD1 = regfile_array[AD1];
        RD2 = regfile_array[AD2];
    end

always_ff @(posedge clk)
    begin
        if(WE3 == 1'b1)
            regfile_array[AD3] <= WD3;
    end

    //synchronous
    assign a0 = regfile_array[{16'b01010}];

endmodule

rtl2/Sign_extend.sv
module Sign_extend (
    input logic [2:0]   ImmSrc,
    input logic [31:0]  instr,
    output logic [31:0] ImmExt
);

    logic dummy_wire;

always_comb

    casez(ImmSrc)
    default: assign dummy_wire = 0; 
    3'b000: if (instr[31])                                      // I type   12 bits immediate is from the instruction bit [31:20]
                assign ImmExt = ({20'hFFFFF, instr[31:20]});
            else
                assign ImmExt = ({20'b0, instr[31:20]});

    3'b001: if (instr[31])                                      // S type 
                assign ImmExt = ({20'hFFFFF, instr[31:25], instr[11:7]});
            else
                assign ImmExt = ({20'b0, instr[31:25], instr[11:7]});

    3'b010: if (instr[31])                                      // B type
                assign ImmExt = ({20'hFFFFF, instr[31], instr[7], instr[30:25], instr[11:8]});
            else
                assign ImmExt = ({20'b0,  instr[31], instr[7], instr[30:25], instr[11:8]});
    
    3'b011: if (instr[31])                                      // J type
                assign ImmExt = ({20'hFFFFF, instr[31], instr[19:12], instr[20], instr[30:21]});
            else
                assign ImmExt = ({20'b0, instr[31], instr[19:12], instr[20], instr[30:21]});

    3'b100: assign ImmExt = ({instr[31:12], 12'b0});            // U type

    endcase
    
endmodule

rtl2/Control_Unit.sv
module Control_Unit (
    input logic         Zero,
    input logic  [31:0] instr,
    output logic        RegWrite,
    output logic [2:0]  ALUctrl,
    output logic        ALUsrc,
    output logic [2:0]  ImmSrc,
    output logic        PCsrc,
    output logic        ResultSrc,
    output logic        MemWrite,
    output logic        MUXJUMP,                // MUXJUMP = 0 so that register write in result. MUXJUMP = 1 so that register write in PC+4
    output logic        JUMPRT     
);

logic [6:0]         op;
logic [2:0]         funct3;
logic [6:0]         funct7;
logic [1:0]         ALUOp;
logic [1:0]         opfunct7;
//logic               Branch;
//logic               dummy;


assign op = instr[6:0];
assign funct3 = instr[14:12];
assign funct7 = instr[31:25];
assign opfunct7 = {op[5],funct7[5]};

always_comb begin
    casez(op)

    default: begin                          //default value
            assign MUXJUMP = 0;
            assign JUMPRT = 0;
            assign PCsrc = 0;
            assign RegWrite = 0;
            assign ImmSrc = 3'b000;
            assign ALUsrc = 0;
            assign MemWrite = 0;
            assign ResultSrc = 0;
            assign ALUOp = 2'b00; 
    end

    7'b0010011: begin                      // Immediate ALU operation
        assign RegWrite = 1;
        assign ImmSrc = 3'b000;
        assign ALUsrc = 1;
        assign MemWrite = 0;
        assign ResultSrc = 0;
        //assign Branch = 0;
        assign ALUOp = 2'b10;
        assign MUXJUMP = 0;
        assign PCsrc = 0;
        assign JUMPRT = 0;
    end

    7'b0000011: begin                     //  Load
        assign RegWrite = 1;
        assign ImmSrc = 3'b000;
        assign ALUsrc = 1;
        assign MemWrite = 0;
        assign ResultSrc = 1;
        //assign Branch = 0;
        assign ALUOp = 2'b00;
        assign MUXJUMP = 0;
        assign PCsrc = 0;
        assign JUMPRT = 0;
    end

    7'b0100011: begin                     // store
        assign RegWrite = 0;
        assign ImmSrc = 3'b001;
        assign ALUsrc = 1;
        assign MemWrite = 1;
        assign ResultSrc = 0;
        //assign Branch = 0;
        assign ALUOp = 2'b00;
        assign MUXJUMP = 0;
        assign PCsrc = 0;
        assign JUMPRT = 0;
    end

    7'b0110011: begin                     // R type
        assign RegWrite = 1;
        assign ImmSrc = 3'b000;
        assign ALUsrc = 0;
        assign MemWrite = 0;
        assign ResultSrc = 0;
        //assign Branch = 0;
        assign ALUOp = 2'b10;
        assign MUXJUMP = 0;
        assign PCsrc = 0;
        assign JUMPRT = 0;
    end

    7'b1100011: begin                      // Branch
        assign RegWrite = 0;
        assign ImmSrc = 3'b010;
        assign ALUsrc = 0;
        assign MemWrite = 0;
        assign ResultSrc = 0;
        //assign Branch = 1;
        assign ALUOp = 2'b01;
        assign MUXJUMP = 0;
        assign JUMPRT = 0;
        
        casez(funct3)
            default: assign PCsrc = 0;
            3'b000: if (Zero)
                        assign PCsrc = 1;
                    else
                        assign PCsrc = 0;
            3'b001: if (Zero)
                        assign PCsrc = 0;
                    else
                        assign PCsrc = 1;
        endcase
    end

    7'b1100111: begin                      // jump and link register
        assign RegWrite = 1;
        assign ImmSrc = 3'b000;
        assign ALUsrc = 1;
        assign MemWrite = 0;
        assign ResultSrc = 0;
        //assign Branch = 1;
        assign ALUOp = 2'b00;
        assign MUXJUMP = 1;
        assign PCsrc = 1;
        assign JUMPRT = 1;
    end

    7'b1101111: begin                      // jump and link
        assign RegWrite = 1;
        assign ImmSrc = 3'b011;
        assign ALUsrc = 0;
        assign MemWrite = 0;
        assign ResultSrc = 0;
        //assign Branch = 1;
        assign ALUOp = 2'b00;
        assign MUXJUMP = 1;
        assign PCsrc = 1;
        assign JUMPRT = 0;
    end

    7'b0110111: begin                      // load upper immediate
        assign RegWrite = 1;
        assign ImmSrc = 3'b100;
        assign ALUsrc = 1;
        assign MemWrite = 0;
        assign ResultSrc = 0;
        //assign Branch = 1;
        assign ALUOp = 2'b11;
        assign MUXJUMP = 0;
        assign PCsrc = 0;
        assign JUMPRT = 0;
    end
    endcase

    casez(ALUOp)
    2'b00: assign ALUctrl = 000;
    2'b01: assign ALUctrl = 001;
    2'b10: casez(funct3)
           3'b000: if (op == 0110011 && opfunct7 == 2'b11)   assign ALUctrl = 3'b001;          //subtract
                   else  assign ALUctrl = 3'b000;                      // add
           3'b010: assign ALUctrl = 3'b101;                            // set less than
           3'b110: assign ALUctrl = 3'b011;                            // or
           3'b111: assign ALUctrl = 3'b010;                            // and
           3'b001: assign ALUctrl = 3'b100;                            // shift left
           endcase
    2'b11: assign ALUctrl = 3'b110;                                       // ALUResult = SrcB
    endcase
end

endmodule

rtl2/Instr_Mem.sv
module Instr_Mem # (
    parameter   ADDRESS_WIDTH = 32,
                DATA_WIDTH = 8,
                OUT_WIDTH = 32
)(
    input logic [ADDRESS_WIDTH-1:0] A,
    output logic [OUT_WIDTH-1:0] RD
);

logic [11:0] addr = A[11:0] ;

logic [DATA_WIDTH-1:0] array [2**12-1:0];

initial begin
        $display ("Loading Instr_Mem.");
        $readmemh("counter.mem", array); 
end;

assign RD = {array [addr+0], array [addr+1], array [addr+2], array[addr+3]};

endmodule

rtl2/ProgramCounter.sv
module ProgramCounter#(
    parameter WIDTH = 32
)(
    input logic      clk,
    input logic      rst,
    input logic [WIDTH-1:0]  PCNext,
    output logic [WIDTH-1:0]  PC
);

always_ff @(posedge clk, posedge rst)
    if(rst) PC <= 32'hBFC00000;
    else    PC <= PCNext;

endmodule

rtl/PC_top.sv
module PC_top #(
    parameter WIDTH = 32
)(
    input logic clk,
    input logic rst,
    input logic PCsrc,
    input logic JUMPRT,
    input logic [WIDTH-1:0] ImmOp,
    input logic [WIDTH-1:0] Result,
    output logic [WIDTH-1:0] PC
);

logic [WIDTH-1:0]  inc_PC;
logic [WIDTH-1:0]  branch_PC;
logic [WIDTH-1:0]  PCNext;
logic [WIDTH-1:0] ReturnMultiplexerOutput;
assign inc_PC = PC+4;
assign branch_PC = PC + ImmOp;

assign ReturnMultiplexerOutput = JUMPRT ? Result : branch_PC;//jump multiplexer
assign PCNext = PCsrc ? ReturnMultiplexerOutput : inc_PC;

  ProgramCounter ProgramCounter (
    .clk (clk),
    .rst (rst),
    .PCNext (PCNext),
    .PC(PC)
  );

endmodule

rtl3/top.sv
module top #(
        parameter ADDRESS_WIDTH = 16,
                  DATA_WIDTH = 32
) (
    input logic clk,
    input logic rst,
    input logic TRIGGERSEL,
    output logic [DATA_WIDTH-1:0] a0
);

//green 
logic [DATA_WIDTH-1:0] instr;
//blue
logic [ADDRESS_WIDTH-1:0] rs1;
logic [ADDRESS_WIDTH-1:0] rs2;
logic [ADDRESS_WIDTH-1:0] rd;
//purple
logic RegWrite;
logic [2:0] ALUctrl;
logic ALUsrc;
logic [2:0] ImmSrc;
logic PCsrc;
logic MemWrite;
logic JUMPRT;
logic MUXJUMP;
logic Zero;
logic ResultSrc;
//yellow
logic [DATA_WIDTH-1:0] ALUop1;
logic [DATA_WIDTH-1:0] ALUop2;
logic [DATA_WIDTH-1:0] regOp2;
logic [DATA_WIDTH-1:0] ALUout;
logic EQ;
//orange
logic [DATA_WIDTH-1:0] ImmOp;
logic [DATA_WIDTH-1:0] PC;
logic [DATA_WIDTH-1:0] MUXJUMPOutput;
//dataMemory
logic [DATA_WIDTH-1:0] ReadData;
logic [DATA_WIDTH-1:0] TriggerOutput;
logic [DATA_WIDTH-1:0] Result;

assign rs1 = {{11'b0},instr[19:15]};
assign rs2 = {{11'b0},instr[24:20]};
assign rd = {{11'b0},instr[11:7]};



PC_top pc_top_instance (
    .clk (clk),
    .rst (rst),
    .ImmOp(ImmOp),
    .PCsrc (PCsrc),
    .PC (PC),
    .JUMPRT(JUMPRT),
    .Result(Result)
);

Instr_Mem instr_mem_instance (
    .A (PC),
    .RD (instr)
);

Control_Unit control_unit_instance(
    .Zero (Zero),
    .instr (instr),
    .RegWrite (RegWrite),
    .ALUctrl (ALUctrl),
    .ALUsrc (ALUsrc),
    .ImmSrc (ImmSrc),
    .PCsrc (PCsrc),
    .ResultSrc (ResultSrc),
    .MemWrite(MemWrite),
    .JUMPRT(JUMPRT),
    .MUXJUMP(MUXJUMP)
);

Sign_extend sign_extend_instance(
    .ImmSrc (ImmSrc),
    .instr (instr),
    .ImmExt (ImmOp)
);

assign MUXJUMPOutput = MUXJUMP ? PC+4 : Result;

RegFile reg_file_instance(
    .clk (clk),
    .AD1 (rs1),
    .AD2 (rs2),
    .AD3 (rd),
    .WE3 (RegWrite),
    .WD3 (MUXJUMPOutput),
    .RD1 (ALUop1),
    .RD2 (regOp2),
    .a0 (a0)
);

assign ALUop2 = ALUsrc ? ImmOp : regOp2;

ALU alu_instance(
    .ALUctrl (ALUctrl),
    .ALUop1 (ALUop1),
    .ALUop2 (ALUop2),
    .ALUResult (ALUout),
    .Zero (Zero)
);

DataMemory data_memory_instance(
    .clk (clk),
    .WE (MemWrite),
    .A (ALUout),
    .WD (regOp2),
    .RD (ReadData)
);

assign TriggerOutput = TRIGGERSEL ? ReadData : ALUout; //Trigger Mux
assign Result = ResultSrc ? TriggerOutput : ALUout; //Mux for data memory


endmodule

rtl2/top.vcd
$version Generated by VerilatedVcd $end
$date Fri Dec  9 10:19:24 2022 $end
$timescale 1ps $end

 $scope module TOP $end
  $var wire  1 B TRIGGERSEL $end
  $var wire 32 C a0 [31:0] $end
  $var wire  1 @ clk $end
  $var wire  1 A rst $end
  $scope module top $end
   $var wire 32 J ADDRESS_WIDTH [31:0] $end
   $var wire  3 ( ALUctrl [2:0] $end
   $var wire 32 1 ALUop1 [31:0] $end
   $var wire 32 2 ALUop2 [31:0] $end
   $var wire 32 4 ALUout [31:0] $end
   $var wire  1 ) ALUsrc $end
   $var wire 32 K DATA_WIDTH [31:0] $end
   $var wire  1 L EQ $end
   $var wire 32 5 ImmOp [31:0] $end
   $var wire  3 * ImmSrc [2:0] $end
   $var wire  1 - JUMPRT $end
   $var wire  1 . MUXJUMP $end
   $var wire 32 D MUXJUMPOutput [31:0] $end
   $var wire  1 , MemWrite $end
   $var wire 32 6 PC [31:0] $end
   $var wire  1 + PCsrc $end
   $var wire 32 E ReadData [31:0] $end
   $var wire  1 ' RegWrite $end
   $var wire 32 G Result [31:0] $end
   $var wire  1 0 ResultSrc $end
   $var wire  1 B TRIGGERSEL $end
   $var wire 32 F TriggerOutput [31:0] $end
   $var wire  1 / Zero $end
   $var wire 32 C a0 [31:0] $end
   $var wire  1 @ clk $end
   $var wire 32 # instr [31:0] $end
   $var wire 16 & rd [15:0] $end
   $var wire 32 3 regOp2 [31:0] $end
   $var wire 16 $ rs1 [15:0] $end
   $var wire 16 % rs2 [15:0] $end
   $var wire  1 A rst $end
   $scope module alu_instance $end
    $var wire 32 4 ALUResult [31:0] $end
    $var wire  3 ( ALUctrl [2:0] $end
    $var wire 32 1 ALUop1 [31:0] $end
    $var wire 32 2 ALUop2 [31:0] $end
    $var wire 32 K DATA_WIDTH [31:0] $end
    $var wire  1 / Zero $end
   $upscope $end
   $scope module control_unit_instance $end
    $var wire  2 : ALUOp [1:0] $end
    $var wire  3 ( ALUctrl [2:0] $end
    $var wire  1 ) ALUsrc $end
    $var wire  3 * ImmSrc [2:0] $end
    $var wire  1 - JUMPRT $end
    $var wire  1 . MUXJUMP $end
    $var wire  1 , MemWrite $end
    $var wire  1 + PCsrc $end
    $var wire  1 ' RegWrite $end
    $var wire  1 0 ResultSrc $end
    $var wire  1 / Zero $end
    $var wire  3 8 funct3 [2:0] $end
    $var wire  7 9 funct7 [6:0] $end
    $var wire 32 # instr [31:0] $end
    $var wire  7 7 op [6:0] $end
    $var wire  2 ; opfunct7 [1:0] $end
   $upscope $end
   $scope module data_memory_instance $end
    $var wire 32 4 A [31:0] $end
    $var wire 32 K ADDRESS_WIDTH [31:0] $end
    $var wire 32 K DATA_WIDTH [31:0] $end
    $var wire 32 E RD [31:0] $end
    $var wire 32 3 WD [31:0] $end
    $var wire  1 , WE $end
    $var wire  1 @ clk $end
   $upscope $end
   $scope module instr_mem_instance $end
    $var wire 32 6 A [31:0] $end
    $var wire 32 K ADDRESS_WIDTH [31:0] $end
    $var wire 32 M DATA_WIDTH [31:0] $end
    $var wire 32 K OUT_WIDTH [31:0] $end
    $var wire 32 # RD [31:0] $end
    $var wire 12 < addr [11:0] $end
   $upscope $end
   $scope module pc_top_instance $end
    $var wire 32 5 ImmOp [31:0] $end
    $var wire  1 - JUMPRT $end
    $var wire 32 6 PC [31:0] $end
    $var wire 32 H PCNext [31:0] $end
    $var wire  1 + PCsrc $end
    $var wire 32 G Result [31:0] $end
    $var wire 32 I ReturnMultiplexerOutput [31:0] $end
    $var wire 32 K WIDTH [31:0] $end
    $var wire 32 > branch_PC [31:0] $end
    $var wire  1 @ clk $end
    $var wire 32 = inc_PC [31:0] $end
    $var wire  1 A rst $end
    $scope module ProgramCounter $end
     $var wire 32 6 PC [31:0] $end
     $var wire 32 H PCNext [31:0] $end
     $var wire 32 K WIDTH [31:0] $end
     $var wire  1 @ clk $end
     $var wire  1 A rst $end
    $upscope $end
   $upscope $end
   $scope module reg_file_instance $end
    $var wire 16 $ AD1 [15:0] $end
    $var wire 16 % AD2 [15:0] $end
    $var wire 16 & AD3 [15:0] $end
    $var wire 32 J ADDRESS_WIDTH [31:0] $end
    $var wire 32 K DATA_WIDTH [31:0] $end
    $var wire 32 1 RD1 [31:0] $end
    $var wire 32 3 RD2 [31:0] $end
    $var wire 32 D WD3 [31:0] $end
    $var wire  1 ' WE3 $end
    $var wire 32 C a0 [31:0] $end
    $var wire  1 @ clk $end
   $upscope $end
   $scope module sign_extend_instance $end
    $var wire 32 5 ImmExt [31:0] $end
    $var wire  3 * ImmSrc [2:0] $end
    $var wire  1 ? dummy_wire $end
    $var wire 32 # instr [31:0] $end
   $upscope $end
  $upscope $end
 $upscope $end
$enddefinitions $end


#0
b00000000000000000000000000000000 #
b0000000000000000 $
b0000000000000000 %
b0000000000000000 &
0'
b000 (
0)
b000 *
0+
0,
0-
0.
0/
00
b00000000000000000000000000000000 1
b00000000000000000000000000000000 2
b00000000000000000000000000000000 3
b00000000000000000000000000000000 4
b00000000000000000000000000000000 5
b00000000000000000000000000000000 6
b0000000 7
b000 8
b0000000 9
b00 :
b00 ;
b000000000000 <
b00000000000000000000000000000100 =
b00000000000000000000000000000000 >
0?
1@
1A
1B
b00000000000000000000000000000000 C
b00000000000000000000000000000000 D
b00000000000000000000000000000000 E
b00000000000000000000000000000000 F
b00000000000000000000000000000000 G
b00000000000000000000000000000000 H
b00000000000000000000000000000000 I
b00000000000000000000000000010000 J
b00000000000000000000000000100000 K
0L
b00000000000000000000000000001000 M
#1
b00000001000000000000101000010011 #
b0000000000010000 %
b0000000000010100 &
1'
1)
b00000000000000000000000000010000 2
b00000000000000000000000000010000 4
b00000000000000000000000000010000 5
b0010011 7
b10 :
b00000000000000000000000000010000 >
0@
b00000000000000000000000000010000 D
b00000000000000000000000000010000 G
b00000000000000000000000000000100 H
b00000000000000000000000000010000 I
#2
b10111111110000000000000000000000 6
b10111111110000000000000000000100 =
b10111111110000000000000000010000 >
1@
0A
b10111111110000000000000000000100 H
b10111111110000000000000000010000 I
#3
0@
#4
b00000000010100000000101010010011 #
b0000000000000101 %
b0000000000010101 &
b00000000000000000000000000000101 2
b00000000000000000000000000000101 4
b00000000000000000000000000000101 5
b10111111110000000000000000000100 6
b000000000100 <
b10111111110000000000000000001000 =
b10111111110000000000000000001001 >
1@
b00000000000000000000000000000101 D
b00000000000000000000000000000101 G
b10111111110000000000000000001000 H
b10111111110000000000000000001001 I
#5
0@
#6
b00000001010110100000010100110011 #
b0000000000010100 $
b0000000000010101 %
b0000000000001010 &
0)
b00000000000000000000000000010000 1
b00000000000000000000000000000101 3
b00000000000000000000000000010101 4
b00000000000000000000000000010101 5
b10111111110000000000000000001000 6
b0110011 7
b10 ;
b000000001000 <
b10111111110000000000000000001100 =
b10111111110000000000000000011101 >
1@
b00000000000000000000000000010101 D
b00000000000000000000000000010101 G
b10111111110000000000000000001100 H
b10111111110000000000000000011101 I
#7
0@
#8
b00000000000000000000000000000000 #
b0000000000000000 $
b0000000000000000 %
b0000000000000000 &
0'
1/
b00000000000000000000000000000000 1
b00000000000000000000000000000000 2
b00000000000000000000000000000000 3
b00000000000000000000000000000000 4
b00000000000000000000000000000000 5
b10111111110000000000000000001100 6
b0000000 7
b00 ;
b000000001100 <
b10111111110000000000000000010000 =
b10111111110000000000000000001100 >
1@
b00000000000000000000000000010101 C
b00000000000000000000000000000000 D
b00000000000000000000000000000000 G
b10111111110000000000000000010000 H
b10111111110000000000000000001100 I
#9
0@
#10
b10111111110000000000000000010000 6
b000000010000 <
b10111111110000000000000000010100 =
b10111111110000000000000000010000 >
1@
b10111111110000000000000000010100 H
b10111111110000000000000000010000 I
#11
0@
#12
b10111111110000000000000000010100 6
b000000010100 <
b10111111110000000000000000011000 =
b10111111110000000000000000010100 >
1@
b10111111110000000000000000011000 H
b10111111110000000000000000010100 I
#13
0@
#14
b10111111110000000000000000011000 6
b000000011000 <
b10111111110000000000000000011100 =
b10111111110000000000000000011000 >
1@
b10111111110000000000000000011100 H
b10111111110000000000000000011000 I
#15
0@
#16
b10111111110000000000000000011100 6
b000000011100 <
b10111111110000000000000000100000 =
b10111111110000000000000000011100 >
1@
b10111111110000000000000000100000 H
b10111111110000000000000000011100 I
#17
0@
#18
b10111111110000000000000000100000 6
b000000100000 <
b10111111110000000000000000100100 =
b10111111110000000000000000100000 >
1@
b10111111110000000000000000100100 H
b10111111110000000000000000100000 I
#19
0@
#20
b10111111110000000000000000100100 6
b000000100100 <
b10111111110000000000000000101000 =
b10111111110000000000000000100100 >
1@
b10111111110000000000000000101000 H
b10111111110000000000000000100100 I
#21
0@
#22
b10111111110000000000000000101000 6
b000000101000 <
b10111111110000000000000000101100 =
b10111111110000000000000000101000 >
1@
b10111111110000000000000000101100 H
b10111111110000000000000000101000 I
#23
0@
#24
b10111111110000000000000000101100 6
b000000101100 <
b10111111110000000000000000110000 =
b10111111110000000000000000101100 >
1@
b10111111110000000000000000110000 H
b10111111110000000000000000101100 I
#25
0@
#26
b10111111110000000000000000110000 6
b000000110000 <
b10111111110000000000000000110100 =
b10111111110000000000000000110000 >
1@
b10111111110000000000000000110100 H
b10111111110000000000000000110000 I
#27
0@
#28
b10111111110000000000000000110100 6
b000000110100 <
b10111111110000000000000000111000 =
b10111111110000000000000000110100 >
1@
b10111111110000000000000000111000 H
b10111111110000000000000000110100 I
#29
0@
#30
b10111111110000000000000000111000 6
b000000111000 <
b10111111110000000000000000111100 =
b10111111110000000000000000111000 >
1@
b10111111110000000000000000111100 H
b10111111110000000000000000111000 I
#31
0@
#32
b10111111110000000000000000111100 6
b000000111100 <
b10111111110000000000000001000000 =
b10111111110000000000000000111100 >
1@
b10111111110000000000000001000000 H
b10111111110000000000000000111100 I
#33
0@
#34
b10111111110000000000000001000000 6
b000001000000 <
b10111111110000000000000001000100 =
b10111111110000000000000001000000 >
1@
b10111111110000000000000001000100 H
b10111111110000000000000001000000 I
#35
0@
#36
b10111111110000000000000001000100 6
b000001000100 <
b10111111110000000000000001001000 =
b10111111110000000000000001000100 >
1@
b10111111110000000000000001001000 H
b10111111110000000000000001000100 I
#37
0@
#38
b10111111110000000000000001001000 6
b000001001000 <
b10111111110000000000000001001100 =
b10111111110000000000000001001000 >
1@
b10111111110000000000000001001100 H
b10111111110000000000000001001000 I
#39
0@
#40
b10111111110000000000000001001100 6
b000001001100 <
b10111111110000000000000001010000 =
b10111111110000000000000001001100 >
1@
b10111111110000000000000001010000 H
b10111111110000000000000001001100 I
#41
0@
#42
b10111111110000000000000001010000 6
b000001010000 <
b10111111110000000000000001010100 =
b10111111110000000000000001010000 >
1@
b10111111110000000000000001010100 H
b10111111110000000000000001010000 I
#43
0@
#44
b10111111110000000000000001010100 6
b000001010100 <
b10111111110000000000000001011000 =
b10111111110000000000000001010100 >
1@
b10111111110000000000000001011000 H
b10111111110000000000000001010100 I
#45
0@
#46
b10111111110000000000000001011000 6
b000001011000 <
b10111111110000000000000001011100 =
b10111111110000000000000001011000 >
1@
b10111111110000000000000001011100 H
b10111111110000000000000001011000 I
#47
0@
#48
b10111111110000000000000001011100 6
b000001011100 <
b10111111110000000000000001100000 =
b10111111110000000000000001011100 >
1@
b10111111110000000000000001100000 H
b10111111110000000000000001011100 I
#49
0@
#50
b10111111110000000000000001100000 6
b000001100000 <
b10111111110000000000000001100100 =
b10111111110000000000000001100000 >
1@
b10111111110000000000000001100100 H
b10111111110000000000000001100000 I
#51
0@
#52
b10111111110000000000000001100100 6
b000001100100 <
b10111111110000000000000001101000 =
b10111111110000000000000001100100 >
1@
b10111111110000000000000001101000 H
b10111111110000000000000001100100 I
#53
0@
#54
b10111111110000000000000001101000 6
b000001101000 <
b10111111110000000000000001101100 =
b10111111110000000000000001101000 >
1@
b10111111110000000000000001101100 H
b10111111110000000000000001101000 I
#55
0@
#56
b10111111110000000000000001101100 6
b000001101100 <
b10111111110000000000000001110000 =
b10111111110000000000000001101100 >
1@
b10111111110000000000000001110000 H
b10111111110000000000000001101100 I
#57
0@
#58
b10111111110000000000000001110000 6
b000001110000 <
b10111111110000000000000001110100 =
b10111111110000000000000001110000 >
1@
b10111111110000000000000001110100 H
b10111111110000000000000001110000 I
#59
0@
#60
b10111111110000000000000001110100 6
b000001110100 <
b10111111110000000000000001111000 =
b10111111110000000000000001110100 >
1@
b10111111110000000000000001111000 H
b10111111110000000000000001110100 I
#61
0@
#62
b10111111110000000000000001111000 6
b000001111000 <
b10111111110000000000000001111100 =
b10111111110000000000000001111000 >
1@
b10111111110000000000000001111100 H
b10111111110000000000000001111000 I
#63
0@
#64
b10111111110000000000000001111100 6
b000001111100 <
b10111111110000000000000010000000 =
b10111111110000000000000001111100 >
1@
b10111111110000000000000010000000 H
b10111111110000000000000001111100 I
#65
0@
#66
b10111111110000000000000010000000 6
b000010000000 <
b10111111110000000000000010000100 =
b10111111110000000000000010000000 >
1@
b10111111110000000000000010000100 H
b10111111110000000000000010000000 I
#67
0@
#68
b10111111110000000000000010000100 6
b000010000100 <
b10111111110000000000000010001000 =
b10111111110000000000000010000100 >
1@
b10111111110000000000000010001000 H
b10111111110000000000000010000100 I
#69
0@
#70
b10111111110000000000000010001000 6
b000010001000 <
b10111111110000000000000010001100 =
b10111111110000000000000010001000 >
1@
b10111111110000000000000010001100 H
b10111111110000000000000010001000 I
#71
0@
#72
b10111111110000000000000010001100 6
b000010001100 <
b10111111110000000000000010010000 =
b10111111110000000000000010001100 >
1@
b10111111110000000000000010010000 H
b10111111110000000000000010001100 I
#73
0@
#74
b10111111110000000000000010010000 6
b000010010000 <
b10111111110000000000000010010100 =
b10111111110000000000000010010000 >
1@
b10111111110000000000000010010100 H
b10111111110000000000000010010000 I
#75
0@
#76
b10111111110000000000000010010100 6
b000010010100 <
b10111111110000000000000010011000 =
b10111111110000000000000010010100 >
1@
b10111111110000000000000010011000 H
b10111111110000000000000010010100 I
#77
0@
#78
b10111111110000000000000010011000 6
b000010011000 <
b10111111110000000000000010011100 =
b10111111110000000000000010011000 >
1@
b10111111110000000000000010011100 H
b10111111110000000000000010011000 I
#79
0@
#80
b10111111110000000000000010011100 6
b000010011100 <
b10111111110000000000000010100000 =
b10111111110000000000000010011100 >
1@
b10111111110000000000000010100000 H
b10111111110000000000000010011100 I
#81
0@
#82
b10111111110000000000000010100000 6
b000010100000 <
b10111111110000000000000010100100 =
b10111111110000000000000010100000 >
1@
b10111111110000000000000010100100 H
b10111111110000000000000010100000 I
#83
0@
#84
b10111111110000000000000010100100 6
b000010100100 <
b10111111110000000000000010101000 =
b10111111110000000000000010100100 >
1@
b10111111110000000000000010101000 H
b10111111110000000000000010100100 I
#85
0@
#86
b10111111110000000000000010101000 6
b000010101000 <
b10111111110000000000000010101100 =
b10111111110000000000000010101000 >
1@
b10111111110000000000000010101100 H
b10111111110000000000000010101000 I
#87
0@
#88
b10111111110000000000000010101100 6
b000010101100 <
b10111111110000000000000010110000 =
b10111111110000000000000010101100 >
1@
b10111111110000000000000010110000 H
b10111111110000000000000010101100 I
#89
0@
#90
b10111111110000000000000010110000 6
b000010110000 <
b10111111110000000000000010110100 =
b10111111110000000000000010110000 >
1@
b10111111110000000000000010110100 H
b10111111110000000000000010110000 I
#91
0@
#92
b10111111110000000000000010110100 6
b000010110100 <
b10111111110000000000000010111000 =
b10111111110000000000000010110100 >
1@
b10111111110000000000000010111000 H
b10111111110000000000000010110100 I
#93
0@
#94
b10111111110000000000000010111000 6
b000010111000 <
b10111111110000000000000010111100 =
b10111111110000000000000010111000 >
1@
b10111111110000000000000010111100 H
b10111111110000000000000010111000 I
#95
0@
#96
b10111111110000000000000010111100 6
b000010111100 <
b10111111110000000000000011000000 =
b10111111110000000000000010111100 >
1@
b10111111110000000000000011000000 H
b10111111110000000000000010111100 I
#97
0@
#98
b10111111110000000000000011000000 6
b000011000000 <
b10111111110000000000000011000100 =
b10111111110000000000000011000000 >
1@
b10111111110000000000000011000100 H
b10111111110000000000000011000000 I
#99
0@
#100
b10111111110000000000000011000100 6
b000011000100 <
b10111111110000000000000011001000 =
b10111111110000000000000011000100 >
1@
b10111111110000000000000011001000 H
b10111111110000000000000011000100 I
#101
0@
#102
b10111111110000000000000011001000 6
b000011001000 <
b10111111110000000000000011001100 =
b10111111110000000000000011001000 >
1@
b10111111110000000000000011001100 H
b10111111110000000000000011001000 I
#103
0@
#104
b10111111110000000000000011001100 6
b000011001100 <
b10111111110000000000000011010000 =
b10111111110000000000000011001100 >
1@
b10111111110000000000000011010000 H
b10111111110000000000000011001100 I
#105
0@
#106
b10111111110000000000000011010000 6
b000011010000 <
b10111111110000000000000011010100 =
b10111111110000000000000011010000 >
1@
b10111111110000000000000011010100 H
b10111111110000000000000011010000 I
#107
0@
#108
b10111111110000000000000011010100 6
b000011010100 <
b10111111110000000000000011011000 =
b10111111110000000000000011010100 >
1@
b10111111110000000000000011011000 H
b10111111110000000000000011010100 I
#109
0@
#110
b10111111110000000000000011011000 6
b000011011000 <
b10111111110000000000000011011100 =
b10111111110000000000000011011000 >
1@
b10111111110000000000000011011100 H
b10111111110000000000000011011000 I
#111
0@
#112
b10111111110000000000000011011100 6
b000011011100 <
b10111111110000000000000011100000 =
b10111111110000000000000011011100 >
1@
b10111111110000000000000011100000 H
b10111111110000000000000011011100 I
#113
0@
